Metadata-Version: 2.4
Name: iflow-mcp_mcp-simple-tool
Version: 0.1.0
Summary: A simple MCP server exposing a website fetching tool
Author: Anthropic, PBC.
Maintainer-email: David Soria Parra <davidsp@anthropic.com>, Justin Spahr-Summers <justin@anthropic.com>
License: MIT
License-File: LICENSE
Keywords: automation,fetch,llm,mcp,web
Classifier: Development Status :: 4 - Beta
Classifier: Intended Audience :: Developers
Classifier: License :: OSI Approved :: MIT License
Classifier: Programming Language :: Python :: 3
Classifier: Programming Language :: Python :: 3.10
Requires-Python: >=3.10
Requires-Dist: anyio>=4.5
Requires-Dist: click>=8.1.0
Requires-Dist: httpx>=0.27
Requires-Dist: mcp
Provides-Extra: dev
Requires-Dist: pyright>=1.1.378; extra == 'dev'
Requires-Dist: pytest-asyncio>=0.23.5; extra == 'dev'
Requires-Dist: pytest>=8.3.3; extra == 'dev'
Requires-Dist: ruff>=0.6.9; extra == 'dev'
